modalities/__init__.py
modalities/__main__.py
modalities/api.py
modalities/batch.py
modalities/evaluator.py
modalities/exceptions.py
modalities/gym.py
modalities/loss_functions.py
modalities/main.py
modalities/trainer.py
modalities/util.py
modalities/checkpointing/__init__.py
modalities/checkpointing/checkpoint_conversion.py
modalities/checkpointing/checkpoint_loading.py
modalities/checkpointing/checkpoint_saving.py
modalities/checkpointing/checkpoint_saving_execution.py
modalities/checkpointing/checkpoint_saving_instruction.py
modalities/checkpointing/checkpoint_saving_strategies.py
modalities/checkpointing/fsdp/__init__.py
modalities/checkpointing/fsdp/fsdp_checkpoint_loading.py
modalities/checkpointing/fsdp/fsdp_checkpoint_saving.py
modalities/checkpointing/stateful/__init__.py
modalities/checkpointing/stateful/app_state.py
modalities/checkpointing/stateful/app_state_factory.py
modalities/checkpointing/torch/__init__.py
modalities/checkpointing/torch/torch_checkpoint_loading.py
modalities/config/__init__.py
modalities/config/component_factory.py
modalities/config/config.py
modalities/config/instantiation_models.py
modalities/config/lookup_enum.py
modalities/config/pydantic_if_types.py
modalities/config/utils.py
modalities/conversion/__init__.py
modalities/conversion/gpt2/__init__.py
modalities/conversion/gpt2/configuration_gpt2.py
modalities/conversion/gpt2/conversion_code.py
modalities/conversion/gpt2/conversion_model.py
modalities/conversion/gpt2/conversion_tokenizer.py
modalities/conversion/gpt2/convert_gpt2.py
modalities/conversion/gpt2/modeling_gpt2.py
modalities/dataloader/__init__.py
modalities/dataloader/apply_chat_template.py
modalities/dataloader/create_index.py
modalities/dataloader/create_instruction_tuning_data.py
modalities/dataloader/create_packed_data.py
modalities/dataloader/dataloader.py
modalities/dataloader/dataloader_factory.py
modalities/dataloader/dataset.py
modalities/dataloader/dataset_factory.py
modalities-0.4.0.dist-info/licenses/LICENSE
modalities-0.4.0.dist-info/METADATA
modalities-0.4.0.dist-info/WHEEL
modalities-0.4.0.dist-info/entry_points.txt
modalities-0.4.0.dist-info/top_level.txt
modalities-0.4.0.dist-info/RECORD
