Metadata-Version: 2.4
Name: modalities
Version: 0.4.0
Summary: Modalities, a PyTorch-native framework for distributed and reproducible foundation model training.
Project-URL: Homepage, https://github.com/Modalities/modalities
Project-URL: Issues, https://github.com/Modalities/modalities/issues
Requires-Python: <3.13,>=3.10
License-File: LICENSE
Requires-Dist: numpy<2.0
Requires-Dist: torch
Requires-Dist: packaging
Requires-Dist: tqdm
Requires-Dist: pyyaml
Requires-Dist: transformers
Requires-Dist: datasets
Requires-Dist: protobuf
Requires-Dist: SentencePiece
Requires-Dist: rich
Requires-Dist: omegaconf
Requires-Dist: pydantic
Requires-Dist: click
Requires-Dist: click_pathlib
Requires-Dist: jq
Requires-Dist: class_resolver
Requires-Dist: wandb
Requires-Dist: einops>=0.7.0
Provides-Extra: linting
Requires-Dist: pre-commit; extra == "linting"
Provides-Extra: tests
Requires-Dist: pytest; extra == "tests"
Requires-Dist: pytest-cov; extra == "tests"
Requires-Dist: debugpy; extra == "tests"
Provides-Extra: install-helper
Requires-Dist: ninja; extra == "install-helper"
Dynamic: license-file
